{
  "id": "terminal-file-drag-path",
  "name": "terminal-file-drag-path",
  "title": "终端支持文件拖拽显示路径",
  "description": "",
  "status": "in_progress",
  "dev_type": null,
  "scope": null,
  "package": null,
  "priority": "P2",
  "creator": "CLI-Manager",
  "assignee": "CLI-Manager",
  "createdAt": "2026-06-24",
  "completedAt": null,
  "branch": null,
  "base_branch": "master",
  "worktree_path": null,
  "commit": null,
  "pr_url": null,
  "subtasks": [],
  "children": [],
  "parent": null,
  "relatedFiles": [],
  "notes": "",
  "meta": {}
}